chandler/__init__.py
chandler/handler.py
chandler_handler-0.0.2.dist-info/LICENSE.txt
chandler_handler-0.0.2.dist-info/METADATA
chandler_handler-0.0.2.dist-info/WHEEL
chandler_handler-0.0.2.dist-info/top_level.txt
chandler_handler-0.0.2.dist-info/RECORD
