Metadata-Version: 2.1
Name: chandler-handler
Version: 0.0.2
Summary: Python Size and Time Based Logging File Rotating Handler
Home-page: https://github.com/suraj-arya/chandler
Author: Suraj Arya
Author-email: Suraj Arya <surajarya@example.com>
Project-URL: Homepage, https://github.com/suraj-arya/chandler
Project-URL: Bug Tracker, https://github.com/suraj-arya/chandler/issues
Keywords: chandler,python logging,logging handlers,python logging rotation,size based,time based
Classifier: Programming Language :: Python :: 3
Classifier: License :: OSI Approved :: MIT License
Classifier: Operating System :: OS Independent
Requires-Python: >=3.7, <4
License-File: LICENSE.txt
Provides-Extra: dev
Requires-Dist: check-manifest ; extra == 'dev'
Provides-Extra: test
Requires-Dist: coverage ; extra == 'test'
